aws_bedrock_token_generator/.token_generator.py.swp
aws_bedrock_token_generator/__init__.py
aws_bedrock_token_generator/token_generator.py
aws_bedrock_token_generator-1.0.1.dist-info/licenses/LICENSE.txt
aws_bedrock_token_generator-1.0.1.dist-info/licenses/NOTICE
aws_bedrock_token_generator-1.0.1.dist-info/METADATA
aws_bedrock_token_generator-1.0.1.dist-info/WHEEL
aws_bedrock_token_generator-1.0.1.dist-info/top_level.txt
aws_bedrock_token_generator-1.0.1.dist-info/RECORD
