Metadata-Version: 2.4
Name: aws-bedrock-token-generator
Version: 1.0.1
Summary: A lightweight library for generating short-term bearer tokens for AWS Bedrock API authentication
Author: Amazon Web Services
License: Apache-2.0
Project-URL: Homepage, https://github.com/aws/aws-bedrock-token-generator-python
Project-URL: Repository, https://github.com/aws/aws-bedrock-token-generator-python
Project-URL: Documentation, https://github.com/aws/aws-bedrock-token-generator-python#readme
Project-URL: Issues, https://github.com/aws/aws-bedrock-token-generator-python/issues
Classifier: Development Status :: 4 - Beta
Classifier: Intended Audience :: Developers
Classifier: License :: OSI Approved :: Apache Software License
Classifier: Operating System :: OS Independent
Classifier: Programming Language :: Python :: 3
Classifier: Programming Language :: Python :: 3.7
Classifier: Programming Language :: Python :: 3.8
Classifier: Programming Language :: Python :: 3.9
Classifier: Programming Language :: Python :: 3.10
Classifier: Programming Language :: Python :: 3.11
Classifier: Programming Language :: Python :: 3.12
Requires-Python: >=3.7
License-File: LICENSE.txt
License-File: NOTICE
Requires-Dist: botocore>=1.33.0
Provides-Extra: dev
Requires-Dist: pytest>=6.0; extra == "dev"
Requires-Dist: pytest-cov>=2.0; extra == "dev"
Requires-Dist: black>=21.0; extra == "dev"
Requires-Dist: flake8>=3.8; extra == "dev"
Requires-Dist: mypy>=0.800; extra == "dev"
Dynamic: license-file
